streamsx/database/__init__.py
streamsx/database/_database.py
streamsx.database-1.6.0.dist-info/DESCRIPTION.rst
streamsx.database-1.6.0.dist-info/LICENSE.txt
streamsx.database-1.6.0.dist-info/METADATA
streamsx.database-1.6.0.dist-info/RECORD
streamsx.database-1.6.0.dist-info/WHEEL
streamsx.database-1.6.0.dist-info/metadata.json
streamsx.database-1.6.0.dist-info/top_level.txt
