Metadata-Version: 2.0
Name: streamsx.database
Version: 1.6.0
Summary: Database integration for IBM Streams
Home-page: https://github.com/IBMStreams/streamsx.database
Author: IBM Streams @ github.com
Author-email: hegermar@de.ibm.com
License: Apache License - Version 2.0
Keywords: streams,ibmstreams,streaming,analytics,streaming-analytics,db2,database
Platform: UNKNOWN
Classifier: Development Status :: 5 - Production/Stable
Classifier: License :: OSI Approved :: Apache Software License
Classifier: Programming Language :: Python :: 3
Classifier: Programming Language :: Python :: 3.5
Classifier: Programming Language :: Python :: 3.6
Classifier: Programming Language :: Python :: 3.7
Requires-Dist: streamsx (>=1.14.6)
Requires-Dist: streamsx.toolkits
